rozetka_wallet/__init__.py
rozetka_wallet-0.0.1.dist-info/METADATA
rozetka_wallet-0.0.1.dist-info/WHEEL
rozetka_wallet-0.0.1.dist-info/top_level.txt
rozetka_wallet-0.0.1.dist-info/RECORD
