Metadata-Version: 2.1
Name: rozetka_wallet
Version: 0.0.1
Summary: rozetka_wallet package lock
